CPE487/Lab2/fsm.vhdl
-- Library and Use Clause
library IEEE;
use IEEE.std_logic_1164.all;
use IEEE.numeric_std.all; -- Include numeric_std for to_unsigned function

-- Reset signal to state A
entity fsm is
    port (
        X, CLK, RESET: in std_logic;
        Y : out std_logic_vector(1 downto 0);
        Z : out std_logic;
        STATE : out std_logic_vector(2 downto 0) -- For simulation only 
    );
end fsm;

architecture fsmMoore11100 of fsm is
    -- Define the enumeration type for states
    type state_type is (A, B, C, D, E, F);
    
    -- Declare signals for present state (PS) and next state (NS)
    signal PS, NS : state_type;
begin 
    -- Clock and Reset Process
    clockAndReset: process(CLK, RESET)
    begin
        -- Initialize the present state (PS) to A when RESET is asserted
        if (RESET = '1') then
            PS <= A;
        elsif (rising_edge(CLK)) then
            -- Update the present state (PS) on a rising clock edge
            PS <= NS;
        end if;

        -- Set the STATE output port based on the current state (PS)
        case PS is
            when A =>
                STATE <= "000";
            when B =>
                STATE <= "001";
            when C =>
                STATE <= "010";
            when D =>
                STATE <= "011";
            when E =>
                STATE <= "100";
            when F =>
                STATE <= "101";
        end case;


    end process clockAndReset;

    -- State and Output Logic Process
    stateAndOutputLogic : process(PS, X)
    begin
        -- Initialize the Z output to '0'
        Z <= '0';

        -- State transition and output logic
        case PS is
            when A =>
                if (X = '1') then
                    NS <= B;
                else
                    NS <= A;
                end if;
            when B =>
                if (X = '1') then
                    NS <= C;
                else
                    NS <= A;
                end if;
            when C =>
                if (X = '1') then
                    NS <= D;
                else
                    NS <= A;
                end if;
            when D =>
                if (X = '0') then
                    NS <= E;
                else
                    NS <= D;
                end if;
            when E =>
                if (X = '0') then
                    NS <= F;
                else
                    NS <= B;
                end if;
            when F =>
                Z <= '1';
                if (X = '0') then
                    NS <= A;
                else
                    NS <= B;
                end if;
        end case;
    end process stateAndOutputLogic;
end fsmMoore11100;

CPE487/Lab2_Old/fsm_tb.vhdl
-- Library and Use Clause
library IEEE;
use IEEE.std_logic_1164.all;

-- Entity for the FSM Test Bench
entity fsm_tb is
end fsm_tb;

architecture tb_arch of fsm_tb is
    -- Declare signals for inputs and outputs
    signal X, CLK, RESET: std_logic;
    signal Y : std_logic_vector(1 downto 0);
    signal Z : std_logic;
    signal STATE : std_logic_vector(2 downto 0);
    
    -- Instantiate the FSM design
    component fsm
        port (
            X, CLK, RESET: in std_logic;
            Y : out std_logic_vector(1 downto 0);
            Z : out std_logic;
            STATE : out std_logic_vector(2 downto 0)
        );
    end component;

   -- Shared variable to control clock generation
    shared variable stop_clock: boolean := false; 
begin
    -- Connect the signals to the FSM
    uut: fsm port map (X, CLK, RESET, Y, Z, STATE);
    
    -- Clock generation process
    process
    begin
        while (not stop_clock) loop
            CLK <= '0';
            wait for 10 ns; -- Adjust the clock period as needed
            CLK <= '1';
            wait for 10 ns;
        end loop;
       wait; 
    end process;

    -- Stimulus process
    process
    begin
        -- Reset the FSM
        RESET <= '1';
        wait for 10 ns;
        RESET <= '0';
        wait for 10 ns;

        -- Test different input patterns
        X <= '0';
        wait for 20 ns;
        
        X <= '1';
        wait for 20 ns;
        
        X <= '0';
        wait for 20 ns;

        -- Add test case for '11100'. This should be the only case where the state goes to F and Z is '1'
        for i in 1 to 3 loop
            X <= '1';
            wait for 20 ns;
        end loop;
        X <= '0';
        wait for 40 ns;

        wait for 20 ns;


        -- End simulation
        stop_clock := true;
        assert false report "End of simulation";
        wait;
    end process;
end tb_arch;

CPE487/Lab2_Old/fsm_tb.vcd
$date
  Tue Oct 31 17:05:09 2023
$end
$version
  GHDL v0
$end
$timescale
  1 fs
$end
$scope module standard $end
$upscope $end
$scope module std_logic_1164 $end
$upscope $end
$scope module numeric_std $end
$upscope $end
$scope module fsm_tb $end
$var reg 1 ! x $end
$var reg 1 " clk $end
$var reg 1 # reset $end
$var reg 2 $ y[1:0] $end
$var reg 1 % z $end
$var reg 3 & state[2:0] $end
$scope module uut $end
$var reg 1 ' x $end
$var reg 1 ( clk $end
$var reg 1 ) reset $end
$var reg 2 * y[1:0] $end
$var reg 1 + z $end
$var reg 3 , state[2:0] $end
$comment ps is not handled $end
$comment ns is not handled $end
$upscope $end
$upscope $end
$enddefinitions $end
#0
U!
0"
1#
bUU $
0%
b000 &
U'
0(
1)
bUU *
0+
b000 ,
#10000000
1"
0#
1(
0)
#20000000
0!
0"
0'
0(
#30000000
1"
1(
#40000000
1!
0"
1'
0(
#50000000
1"
1(
#60000000
0!
0"
b001 &
0'
0(
b001 ,
#70000000
1"
1(
#80000000
1!
0"
b000 &
1'
0(
b000 ,
#90000000
1"
1(
#100000000
0"
b001 &
0(
b001 ,
#110000000
1"
1(
#120000000
0"
b010 &
0(
b010 ,
#130000000
1"
1(
#140000000
0!
0"
b011 &
0'
0(
b011 ,
#150000000
1"
1(
#160000000
0"
b100 &
0(
b100 ,
#170000000
1"
1%
1(
1+
#180000000
0"
b101 &
0(
b101 ,
#190000000
1"
0%
1(
0+
#200000000
0"
b000 &
0(
b000 ,
