CPE487/HybridMealyMooreMachine/MealyMoore.vhdl
library IEEE;
use IEEE.std_logic_1164.all;

entity MealyMoore is
    port (
        -- Input ports X,CLK,RESET
        -- Output ports Y (2 bits),Z1,Z2
        X : in std_logic; -- Input X 
        CLK : in std_logic; -- Clock - A rising edge triggers the state machine
        RESET : in std_logic; -- Reset - A high value resets the state machine
        Y : out std_logic_vector(1 downto 0); -- Output Y (The Top Number)
        Z1 : out std_logic; -- Output Z1 (The Bottom Number)
        Z2 : out std_logic -- Output Z2 (The Output Of The State Machine (new input/ new Z2)

    );
end MealyMoore;

architecture Exercise1 of MealyMoore is
    -- Define the State Types up to ST3
    type StateType is (ST0,ST1,ST2,ST3);

    -- Keep Track of the Current State (Default to ST0)
    signal CurrentState : StateType := ST0;
    -- Keep Track of the Next State 
    signal NextState : StateType;

    begin -- Start of the architecture

    -- Create a process to for the reset and clock
    process (CLK,RESET) begin
        -- If the reset is high then reset the state machine
        if RESET = '1' then
            CurrentState <= ST0;
        -- If the clock is rising edge then update the state machine
        elsif rising_edge(CLK) and CLK = '1' then -- The rising_edge() function is a standard function in VHDL
            CurrentState <= NextState;
        end if;
    end process;

    -- Create a process to update the next state based on certain logic 
    process (CurrentState,X) begin
        -- A: 1/0 -> ST1, 0/0 -> ST0
        if CurrentState = ST0 then 
            if X = '0' then
                Z1 <= '0';
                NextState <= ST0;
            else
                Z1 <= '0';
                NextState <= ST1;
            end if;
        end if;

        -- B: 1/0 -> ST2, 0/0 -> ST0
        if CurrentState = ST1 then 
            if X = '0' then
                Z1 <= '0';
                NextState <= ST0;
            else
                Z1 <= '0';
                NextState <= ST2;
            end if;
        end if;
        
        -- C: 1/0 -> ST2, 0/0 -> ST3
        if CurrentState = ST2 then 
            if X = '0' then
                Z1 <= '0';
                NextState <= ST3;
            else
                Z1 <= '0';
                NextState <= ST2;
            end if;
        end if;

        -- D: 1/1 -> ST1, 0/0 -> ST0
        if CurrentState = ST3 then 
            if X = '0' then
                Z1 <= '0';
                NextState <= ST0;
            else
                Z1 <= '1';
                NextState <= ST1;
            end if;
        end if;
    end process;

    with CurrentState select
        -- Output Y based on the current state
        Y <= "00" when ST0,
             "01" when ST1,
             "10" when ST2,
             "11" when ST3,
             "00" when others;
end Exercise1;

CPE487/HybridMealyMooreMachine/MealyMoore_test.vhdl
library IEEE;
use IEEE.std_logic_1164.all;

entity MealyMoore_test is
end MealyMoore_test;

architecture testbench of MealyMoore_test is
    -- Declare signals for connecting to the MealyMoore entity
    signal X : std_logic := '0';  -- Input X
    signal CLK : std_logic := '0';  -- Clock signal
    signal RESET : std_logic := '0';  -- Reset signal
    signal Y : std_logic_vector(1 downto 0);  -- Output Y
    signal Z1 : std_logic;  -- Output Z1
    signal Z2 : std_logic;  -- Output Z2

    -- Instantiate the MealyMoore entity
    component MealyMoore
        port (
            X : in std_logic;
            CLK : in std_logic;
            RESET : in std_logic;
            Y : out std_logic_vector(1 downto 0);
            Z1 : out std_logic;
            Z2 : out std_logic
        );
    end component;

begin
    -- Instantiate the MealyMoore entity
    UUT: MealyMoore
        port map (
            X => X,
            CLK => CLK,
            RESET => RESET,
            Y => Y,
            Z1 => Z1,
            Z2 => Z2
        );

    -- Clock generation process
    process
    begin
        while now < 100 ns loop  -- Simulate for 100 ns
            CLK <= '0';
            wait for 5 ns;  -- 10 ns clock period
            CLK <= '1';
            wait for 5 ns;
        end loop;
        wait;
    end process;

    -- Test case process
    process
    begin
        -- Initialize/reset the MealyMoore state machine
        RESET <= '1';
        wait for 10 ns;
        RESET <= '0';

        -- Test case 1
        X <= '1';  -- Input X for case A
        wait for 20 ns;

        -- Test case 2
        X <= '0';  -- Input X for case B
        wait for 20 ns;

        -- Test case 3
        X <= '1';  -- Input X for case C
        wait for 20 ns;

        -- Test case 4
        X <= '1';  -- Input X for case D
        wait for 20 ns;

        -- Add more test cases as needed

        -- End simulation
        wait;
    end process;
end testbench;

CPE487/HybridMealyMooreMachine/MealyMoore_test.vcd
$date
  Thu Oct  5 13:42:23 2023
$end
$version
  GHDL v0
$end
$timescale
  1 fs
$end
$scope module standard $end
$upscope $end
$scope module std_logic_1164 $end
$upscope $end
$scope module mealymoore_test $end
$var reg 1 ! x $end
$var reg 1 " clk $end
$var reg 1 # reset $end
$var reg 2 $ y[1:0] $end
$var reg 1 % z1 $end
$var reg 1 & z2 $end
$scope module uut $end
$var reg 1 ' x $end
$var reg 1 ( clk $end
$var reg 1 ) reset $end
$var reg 2 * y[1:0] $end
$var reg 1 + z1 $end
$var reg 1 , z2 $end
$comment currentstate is not handled $end
$comment nextstate is not handled $end
$upscope $end
$upscope $end
$enddefinitions $end
#0
0!
0"
1#
b00 $
0%
U&
0'
0(
1)
b00 *
0+
U,
#5000000
1"
1(
#10000000
1!
0"
0#
1'
0(
0)
#15000000
1"
b01 $
1(
b01 *
#20000000
0"
0(
#25000000
1"
b10 $
1(
b10 *
#30000000
0!
0"
0'
0(
#35000000
1"
b11 $
1(
b11 *
#40000000
0"
0(
#45000000
1"
b00 $
1(
b00 *
#50000000
1!
0"
1'
0(
#55000000
1"
b01 $
1(
b01 *
#60000000
0"
0(
#65000000
1"
b10 $
1(
b10 *
